hqg/__init__.py
hqg/analysis/metrics.py
hqg/api/__init__.py
hqg/api/algorithm.py
hqg/config/config.py
hqg/data/feed.py
hqg/data/loader.py
hqg/data/storage.py
hqg/data/types.py
hqg/data/sources/base.py
hqg/data/sources/ibkr.py
hqg/data/sources/yfinance.py
hqg/engine/backtester.py
hqg/engine/loop.py
hqg/execution/broker.py
hqg-0.1.0.dist-info/METADATA
hqg-0.1.0.dist-info/WHEEL
hqg-0.1.0.dist-info/RECORD
