Metadata-Version: 2.4
Name: hqg
Version: 0.1.0
Summary: A modular backtesting framework for quantitative strategies.
Project-URL: Homepage, https://github.com/Husky-Quantitative-Group/hqg-backtester
Project-URL: Repository, https://github.com/Husky-Quantitative-Group/hqg-backtester
Project-URL: Documentation, https://hqg-backtester.readthedocs.io/
Author-email: Husky Quantitative Group <contact@hqg.org>
Requires-Python: >=3.10
Requires-Dist: ib-insync>=0.9.86
Requires-Dist: matplotlib>=3.7.0
Requires-Dist: numpy>=1.24.0
Requires-Dist: pandas>=2.0.0
Requires-Dist: pyarrow>=12.0.0
Requires-Dist: pyyaml>=6.0
Requires-Dist: scipy>=1.11.0
Requires-Dist: seaborn>=0.12.0
Requires-Dist: yfinance>=0.2.0
Provides-Extra: dev
Requires-Dist: black>=23.0.0; extra == 'dev'
Requires-Dist: isort>=5.12.0; extra == 'dev'
Requires-Dist: mypy>=1.5.0; extra == 'dev'
Requires-Dist: pre-commit>=3.4.0; extra == 'dev'
Requires-Dist: pytest>=7.4.0; extra == 'dev'
Requires-Dist: ruff>=0.1.0; extra == 'dev'
